ruslat/__init__.py
ruslat/command_line.py
ruslat/conversion_tables.py
ruslat/converter.py
ruslat/cyrillic_ortho_fixer.py
ruslat-1.2.0.dist-info/entry_points.txt
ruslat-1.2.0.dist-info/LICENSE
ruslat-1.2.0.dist-info/WHEEL
ruslat-1.2.0.dist-info/METADATA
ruslat-1.2.0.dist-info/RECORD
