Metadata-Version: 2.1
Name: ruslat
Version: 1.2.0
Summary: Transliterator for Russian Latin Alphabet
Home-page: https://github.com/ZetaFactorial/ruslat
License: MIT
Keywords: russian,transliteration,romanization
Author: Zeta Factorial
Requires-Python: >=3.10,<4.0
Classifier: Development Status :: 4 - Beta
Classifier: Intended Audience :: Developers
Classifier: Intended Audience :: Science/Research
Classifier: License :: OSI Approved :: MIT License
Classifier: Natural Language :: Russian
Classifier: Operating System :: OS Independent
Classifier: Programming Language :: Python :: 3
Classifier: Programming Language :: Python :: 3.10
Classifier: Topic :: Software Development :: Libraries :: Python Modules
Classifier: Topic :: Text Processing :: Linguistic
Requires-Dist: regex (>=2022.9.13,<2023.0.0)
Project-URL: Repository, https://github.com/ZetaFactorial/ruslat
